onvo/__init__.py
onvo/base_resource.py
onvo/onvo.py
onvo/resources/accounts.py
onvo/resources/automations.py
onvo/resources/dashboard.py
onvo/resources/dashboards.py
onvo/resources/datasources.py
onvo/resources/embed_users.py
onvo/resources/questions.py
onvo/resources/sessions.py
onvo/resources/teams.py
onvo/resources/widgets.py
onvo/resources/dashboard_resources/__init__.py
onvo/resources/dashboard_resources/base_resource.py
onvo/resources/dashboard_resources/datasources.py
onvo-0.2.0.dist-info/LICENSE
onvo-0.2.0.dist-info/METADATA
onvo-0.2.0.dist-info/WHEEL
onvo-0.2.0.dist-info/top_level.txt
onvo-0.2.0.dist-info/RECORD
