Metadata-Version: 2.1
Name: onvo
Version: 0.2.0
Summary: Communicate with the Onvo platform.
Author-email: Bryan Davis <bryandavis999.dev@gmail.com>
Project-URL: Homepage, https://github.com/onvo-ai/sdks
Project-URL: Issues, https://github.com/onvo-ai/sdks/issues
Keywords: python,onvo
Classifier: Development Status :: 3 - Alpha
Classifier: Intended Audience :: Developers
Classifier: Operating System :: OS Independent
Classifier: Programming Language :: Python :: 3
Classifier: License :: OSI Approved :: MIT License
Requires-Python: >=3.8
License-File: LICENSE
